robo_env/__init__.py
robo_env/envs/__init__.py
robo_env/envs/robo_env.py
robo_env-0.0.1.dist-info/METADATA
robo_env-0.0.1.dist-info/WHEEL
robo_env-0.0.1.dist-info/top_level.txt
robo_env-0.0.1.dist-info/RECORD
