Metadata-Version: 2.1
Name: robo-env
Version: 0.0.1
Summary: A OpenAI 
Home-page: UNKNOWN
License: UNKNOWN
Platform: UNKNOWN
Requires-Dist: gym
